objects_defender
