Metadata-Version: 1.1
Name: django-objects-defender
Version: 1.11
Summary: Easy solution to make undeleteble objects.
Home-page: https://bitbucket.org/datysho/django-objects-defender/
Author: Mikhail Andreev
Author-email: datysho@gmail.com
License: UNKNOWN
Platform: UNKNOWN
Classifier: Framework :: Django
Classifier: Intended Audience :: Developers
Classifier: License :: OSI Approved :: BSD License
Classifier: Operating System :: OS Independent
Classifier: Topic :: Utilities
Requires: django (>=1.4)
